Workbook

Sheet TUDO EM INFORMÁTICA
A1: TUDO EM INFORMÁTICA - Vendas 1º Trimestre 2018
A2: Filial | B2: Mês | C2: Produto | D2: Quantidade | E2: Valor Unitário | F2: Valor Total
A3: Vila Mariana | B3: Janeiro | C3: Mesa para computador | D3: 56 | E3: 230 | F3: =PRODUCT(D3,E3) -> 12880
A4: Vila Mariana | B4: Janeiro | C4: Mouse | D4: 134 | E4: 23.8 | F4: =PRODUCT(D4,E4) -> 3189.2
A5: Brooklin | B5: Janeiro | C5: Mesa para computador | D5: 23 | E5: 247 | F5: =PRODUCT(D5,E5) -> 5681
A6: Vila Mariana | B6: Janeiro | C6: Impressora | D6: 12 | E6: 299 | F6: =PRODUCT(D6,E6) -> 3588
A7: Brooklin | B7: Janeiro | C7: Impressora | D7: 45 | E7: 250 | F7: =PRODUCT(D7,E7) -> 11250
A8: Vila Mariana | B8: Fevereiro | C8: Mesa para computador | D8: 56 | E8: 220 | F8: =PRODUCT(D8,E8) -> 12320
A9: Brooklin | B9: Fevereiro | C9: Mesa para computador | D9: 7 | E9: 210 | F9: =PRODUCT(D9,E9) -> 1470
A10: Vila Mariana | B10: Fevereiro | C10: Mouse | D10: 22 | E10: 25 | F10: =PRODUCT(D10,E10) -> 550
A11: Vila Mariana | B11: Fevereiro | C11: Impressora | D11: 14 | E11: 250 | F11: =PRODUCT(D11,E11) -> 3500
A12: Brooklin | B12: Fevereiro | C12: Mouse | D12: 3 | E12: 20 | F12: =PRODUCT(D12,E12) -> 60
A13: Brooklin | B13: Março | C13: Mesa para computador | D13: 21 | E13: 220 | F13: =PRODUCT(D13,E13) -> 4620
A14: Vila Mariana | B14: Março | C14: Mesa para computador | D14: 18 | E14: 230 | F14: =PRODUCT(D14,E14) -> 4140
... A16: Brooklin | B16: Março | C16: Impressora | D16: 22 | E16: 299 | F16: =PRODUCT(D16,E16) -> 6578
A18: RESUMO DO TRIMESTRE
A19: Número de itens vendidos: | D19: =SUM(D3:D16) -> 466
A20: Valor total de vendas: | D20: =SUMPRODUCT(D3:D16,E3:E16) -> 70486.2
A21: Valor total Vila Mariana: | D21: =SUMIF(A3:A16,"Vila Mariana",F3:F16) -> 40827.2
A22: Valor total Brooklin: | D22: =SUMIF(A3:A16,"Brooklin",F3:F16) -> 29659
A23: Valor total Janeiro: | D23: =SUMIF(B3:B16,"Janeiro",F3:F16) -> 36588.2
A24: Valor total Fevereiro: | D24: =SUMIF(B3:B16,"Fevereiro",F3:F16) -> 17900
A25: Valor total Março: | D25: =SUMIF(B3:B16,"Março",F3:F16) -> 15998
A26: Valor Vila Mariana em Fevereiro: | D26: =SUMIFS(F3:F16,A3:A16,"Vila Mariana",B3:B16,"Fevereiro") -> 16370
A27: Valor Brooklin em Janeiro: | D27: =SUMIFS(F3:F16,A3:A16,"Brooklin",B3:B16,"Janeiro") -> 16931

Sheet LOTERIA
A1: NÚMEROS DA SORTE
A3: NÚMERO 1 | B3: NÚMERO 2 | C3: NÚMERO 3 | D3: NÚMERO 4 | E3: NÚMERO 5 | F3: NÚMERO 6
A4: =RANDBETWEEN(1,60) -> 27 | B4: =RANDBETWEEN(1,60) -> 33 | C4: =RANDBETWEEN(1,60) -> 4 | D4: =RANDBETWEEN(1,60) -> 49 | E4: =RANDBETWEEN(1,60) -> 7 | F4: =RANDBETWEEN(1,60) -> 49

Sheet MEGASENA 2012
A1: CONCURSO | B1: DATA | C1: NÚMEROS SORTEADOS | K1: APOSTA PARA GANHAR
A2: 1351 | B2: 40912 | C2: 13 | D2: 50 | E2: 41 | F2: 36 | G2: 56 | H2: 33 | K2: =RANDBETWEEN(1,60) -> 46 | L2: =RANDBETWEEN(1,60) -> 31 | M2: =RANDBETWEEN(1,60) -> 39 | N2: =RANDBETWEEN(1,60) -> 3 | O2: =RANDBETWEEN(1,60) -> 49 | P2: =_xlfn.MODE.SNGL(C2:H53) -> 27
A3: 1352 | B3: 40915 | C3: 35 | D3: 59 | E3: 36 | F3: 9 | G3: 18 | H3: 24
A4: 1353 | B4: 40919 | C4: 47 | D4: 11 | E4: 3 | F4: 27 | G4: 32 | H4: 13
A5: 1354 | B5: 40922 | C5: 2 | D5: 42 | E5: 8 | F5: 49 | G5: 48 | H5: 38
A6: 1355 | B6: 40926 | C6: 39 | D6: 49 | E6: 11 | F6: 24 | G6: 17 | H6: 46
A7: 1356 | B7: 40929 | C7: 21 | D7: 46 | E7: 6 | F7: 22 | G7: 13 | H7: 31
A8: 1357 | B8: 40933 | C8: 55 | D8: 52 | E8: 26 | F8: 19 | G8: 1 | H8: 24
A9: 1358 | B9: 40936 | C9: 16 | D9: 15 | E9: 37 | F9: 3 | G9: 35 | H9: 47
A10: 1359 | B10: 40940 | C10: 12 | D10: 17 | E10: 28 | F10: 53 | G10: 6 | H10: 10
A11: 1360 | B11: 40943 | C11: 50 | D11: 25 | E11: 17 | F11: 16 | G11: 54 | H11: 2
A12: 1361 | B12: 40947 | C12: 37 | D12: 27 | E12: 44 | F12: 30 | G12: 38 | H12: 23
A13: 1362 | B13: 40950 | C13: 58 | D13: 19 | E13: 12 | F13: 22 | G13: 2 | H13: 36
A14: 1363 | B14: 40954 | C14: 52 | D14: 25 | E14: 42 | F14: 45 | G14: 35 | H14: 57
... A53: 1402 | B53: 41090 | C53: 38 | D53: 10 | E53: 27 | F53: 2 | G53: 21 | H53: 9

Sheet VENDAS
A1: Valor do Prêmio | B1: 50000 | C1: Meta: | D1: 130000
A2: VENDEDOR | B2: DEPARTAMENTO | C2: VALOR DA VENDA (R$) | D2: COLOCAÇÃO | E2: VALOR DO PRÊMIO | F2: CONCEITO | G2: PRÊMIO EXTRA
A3: Máximo Queiroz | B3: USADOS | C3: 100000 | D3: =IFERROR(_xlfn.RANK.EQ(C3,$C$3:$C$22),"") -> 12 | E3: =IF(D3=1,$B$1/[1]RELATÓRIO!$B$10,0) -> 0 | F3: =IF(D3=1,"EXCELENTE",IF(C3>$D$1,"ÓTIMO", IF(C3=$D$1,"BOM","PODE MELHORAR"))) -> PODE MELHORAR | G3: =IF(F3="ÓTIMO","Viagem para Natal",IF(AND(C3<=$D$1, C3 >= 100000),"Computador","")) -> Computador
A4: Maria Amélia Gouveia | B4: ZERO KM | C4: 134600 | D4: =IFERROR(_xlfn.RANK.EQ(C4,$C$3:$C$22),"") -> 6 | E4: =IF(D4=1,$B$1/[1]RELATÓRIO!$B$10,0) -> 0 | F4: =IF(D4=1,"EXCELENTE",IF(C4>$D$1,"ÓTIMO", IF(C4=$D$1,"BOM","PODE MELHORAR"))) -> ÓTIMO | G4: =IF(F4="ÓTIMO","Viagem para Natal",IF(AND(C4<=$D$1, C4 >= 100000),"Computador","")) -> Viagem para Natal
A5: Fernando Augusto Martinez | B5: ISENÇÕES | C5: 50000 | D5: =IFERROR(_xlfn.RANK.EQ(C5,$C$3:$C$22),"") -> 17 | E5: =IF(D5=1,$B$1/[1]RELATÓRIO!$B$10,0) -> 0 | F5: =IF(D5=1,"EXCELENTE",IF(C5>$D$1,"ÓTIMO", IF(C5=$D$1,"BOM","PODE MELHORAR"))) -> PODE MELHORAR | G5: =IF(F5="ÓTIMO","Viagem para Natal",IF(AND(C5<=$D$1, C5 >= 100000),"Computador",""))
A6: Solange Farias | B6: ZERO KM | C6: 130000 | D6: =IFERROR(_xlfn.RANK.EQ(C6,$C$3:$C$22),"") -> 8 | E6: =IF(D6=1,$B$1/[1]RELATÓRIO!$B$10,0) -> 0 | F6: =IF(D6=1,"EXCELENTE",IF(C6>$D$1,"ÓTIMO", IF(C6=$D$1,"BOM","PODE MELHORAR"))) -> BOM | G6: =IF(F6="ÓTIMO","Viagem para Natal",IF(AND(C6<=$D$1, C6 >= 100000),"Computador","")) -> Computador
A7: Luciana Meirelles | B7: ZERO KM | C7: 90870 | D7: =IFERROR(_xlfn.RANK.EQ(C7,$C$3:$C$22),"") -> 13 | E7: =IF(D7=1,$B$1/[1]RELATÓRIO!$B$10,0) -> 0 | F7: =IF(D7=1,"EXCELENTE",IF(C7>$D$1,"ÓTIMO", IF(C7=$D$1,"BOM","PODE MELHORAR"))) -> PODE MELHORAR | G7: =IF(F7="ÓTIMO","Viagem para Natal",IF(AND(C7<=$D$1, C7 >= 100000),"Computador",""))
A8: Geraldo Maximiliano | B8: USADOS | C8: 67800 | D8: =IFERROR(_xlfn.RANK.EQ(C8,$C$3:$C$22),"") -> 16 | E8: =IF(D8=1,$B$1/[1]RELATÓRIO!$B$10,0) -> 0 | F8: =IF(D8=1,"EXCELENTE",IF(C8>$D$1,"ÓTIMO", IF(C8=$D$1,"BOM","PODE MELHORAR"))) -> PODE MELHORAR | G8: =IF(F8="ÓTIMO","Viagem para Natal",IF(AND(C8<=$D$1, C8 >= 100000),"Computador",""))
A9: Stella Cruz e Souza | B9: USADOS | C9: 45000 | D9: =IFERROR(_xlfn.RANK.EQ(C9,$C$3:$C$22),"") -> 18 | E9: =IF(D9=1,$B$1/[1]RELATÓRIO!$B$10,0) -> 0 | F9: =IF(D9=1,"EXCELENTE",IF(C9>$D$1,"ÓTIMO", IF(C9=$D$1,"BOM","PODE MELHORAR"))) -> PODE MELHORAR | G9: =IF(F9="ÓTIMO","Viagem para Natal",IF(AND(C9<=$D$1, C9 >= 100000),"Computador",""))
A10: Marineide Novais | B10: USADOS | C10: 137000 | D10: =IFERROR(_xlfn.RANK.EQ(C10,$C$3:$C$22),"") -> 5 | E10: =IF(D10=1,$B$1/[1]RELATÓRIO!$B$10,0) -> 0 | F10: =IF(D10=1,"EXCELENTE",IF(C10>$D$1,"ÓTIMO", IF(C10=$D$1,"BOM","PODE MELHORAR"))) -> ÓTIMO | G10: =IF(F10="ÓTIMO","Viagem para Natal",IF(AND(C10<=$D$1, C10 >= 100000),"Computador","")) -> Viagem para Natal
A11: Gilda Soares | B11: ISENÇÕES | C11: 23000 | D11: =IFERROR(_xlfn.RANK.EQ(C11,$C$3:$C$22),"") -> 19 | E11: =IF(D11=1,$B$1/[1]RELATÓRIO!$B$10,0) -> 0 | F11: =IF(D11=1,"EXCELENTE",IF(C11>$D$1,"ÓTIMO", IF(C11=$D$1,"BOM","PODE MELHORAR"))) -> PODE MELHORAR | G11: =IF(F11="ÓTIMO","Viagem para Natal",IF(AND(C11<=$D$1, C11 >= 100000),"Computador",""))
A12: Hector Mangiolii | B12: ZERO KM | C12: 149000 | D12: =IFERROR(_xlfn.RANK.EQ(C12,$C$3:$C$22),"") -> 3 | E12: =IF(D12=1,$B$1/[1]RELATÓRIO!$B$10,0) -> 0 | F12: =IF(D12=1,"EXCELENTE",IF(C12>$D$1,"ÓTIMO", IF(C12=$D$1,"BOM","PODE MELHORAR"))) -> ÓTIMO | G12: =IF(F12="ÓTIMO","Viagem para Natal",IF(AND(C12<=$D$1, C12 >= 100000),"Computador","")) -> Viagem para Natal
A13: Marli Vieira | B13: ISENÇÕES | C13: 134000 | D13: =IFERROR(_xlfn.RANK.EQ(C13,$C$3:$C$22),"") -> 7 | E13: =IF(D13=1,$B$1/[1]RELATÓRIO!$B$10,0) -> 0 | F13: =IF(D13=1,"EXCELENTE",IF(C13>$D$1,"ÓTIMO", IF(C13=$D$1,"BOM","PODE MELHORAR"))) -> ÓTIMO | G13: =IF(F13="ÓTIMO","Viagem para Natal",IF(AND(C13<=$D$1, C13 >= 100000),"Computador","")) -> Viagem para Natal
A14: Homero Gamberin | B14: USADOS | C14: 123000 | D14: =IFERROR(_xlfn.RANK.EQ(C14,$C$3:$C$22),"") -> 9 | E14: =IF(D14=1,$B$1/[1]RELATÓRIO!$B$10,0) -> 0 | F14: =IF(D14=1,"EXCELENTE",IF(C14>$D$1,"ÓTIMO", IF(C14=$D$1,"BOM","PODE MELHORAR"))) -> PODE MELHORAR | G14: =IF(F14="ÓTIMO","Viagem para Natal",IF(AND(C14<=$D$1, C14 >= 100000),"Computador","")) -> Computador
... A16: Luci Pereira | B16: ISENÇÕES | C16: 150000 | D16: =IFERROR(_xlfn.RANK.EQ(C16,$C$3:$C$22),"") -> 1 | E16: =IF(D16=1,$B$1/[1]RELATÓRIO!$B$10,0) -> 25000 | F16: =IF(D16=1,"EXCELENTE",IF(C16>$D$1,"ÓTIMO", IF(C16=$D$1,"BOM","PODE MELHORAR"))) -> EXCELENTE | G16: =IF(F16="ÓTIMO","Viagem para Natal",IF(AND(C16<=$D$1, C16 >= 100000),"Computador",""))
A17: Marcela Gianotti | B17: ISENÇÕES | D17: =IFERROR(_xlfn.RANK.EQ(C17,$C$3:$C$22),"") | E17: =IF(D17=1,$B$1/[1]RELATÓRIO!$B$10,0) -> 0 | F17: =IF(D17=1,"EXCELENTE",IF(C17>$D$1,"ÓTIMO", IF(C17=$D$1,"BOM","PODE MELHORAR"))) -> PODE MELHORAR | G17: =IF(F17="ÓTIMO","Viagem para Natal",IF(AND(C17<=$D$1, C17 >= 100000),"Computador",""))
A18: Arlete Farias | B18: USADOS | C18: 120000 | D18: =IFERROR(_xlfn.RANK.EQ(C18,$C$3:$C$22),"") -> 11 | E18: =IF(D18=1,$B$1/[1]RELATÓRIO!$B$10,0) -> 0 | F18: =IF(D18=1,"EXCELENTE",IF(C18>$D$1,"ÓTIMO", IF(C18=$D$1,"BOM","PODE MELHORAR"))) -> PODE MELHORAR | G18: =IF(F18="ÓTIMO","Viagem para Natal",IF(AND(C18<=$D$1, C18 >= 100000),"Computador","")) -> Computador
A19: Beatriz Domingues | B19: ZERO KM | C19: 87900 | D19: =IFERROR(_xlfn.RANK.EQ(C19,$C$3:$C$22),"") -> 14 | E19: =IF(D19=1,$B$1/[1]RELATÓRIO!$B$10,0) -> 0 | F19: =IF(D19=1,"EXCELENTE",IF(C19>$D$1,"ÓTIMO", IF(C19=$D$1,"BOM","PODE MELHORAR"))) -> PODE MELHORAR | G19: =IF(F19="ÓTIMO","Viagem para Natal",IF(AND(C19<=$D$1, C19 >= 100000),"Computador",""))
A20: Camila Gonçalves | B20: ZERO KM | C20: 123000 | D20: =IFERROR(_xlfn.RANK.EQ(C20,$C$3:$C$22),"") -> 9 | E20: =IF(D20=1,$B$1/[1]RELATÓRIO!$B$10,0) -> 0 | F20: =IF(D20=1,"EXCELENTE",IF(C20>$D$1,"ÓTIMO", IF(C20=$D$1,"BOM","PODE MELHORAR"))) -> PODE MELHORAR | G20: =IF(F20="ÓTIMO","Viagem para Natal",IF(AND(C20<=$D$1, C20 >= 100000),"Computador","")) -> Computador
A21: Rogério Hanibal Junior | B21: USADOS | C21: 76900 | D21: =IFERROR(_xlfn.RANK.EQ(C21,$C$3:$C$22),"") -> 15 | E21: =IF(D21=1,$B$1/[1]RELATÓRIO!$B$10,0) -> 0 | F21: =IF(D21=1,"EXCELENTE",IF(C21>$D$1,"ÓTIMO", IF(C21=$D$1,"BOM","PODE MELHORAR"))) -> PODE MELHORAR | G21: =IF(F21="ÓTIMO","Viagem para Natal",IF(AND(C21<=$D$1, C21 >= 100000),"Computador",""))
A22: Katia Domenica Lira | B22: USADOS | C22: 143000 | D22: =IFERROR(_xlfn.RANK.EQ(C22,$C$3:$C$22),"") -> 4 | E22: =IF(D22=1,$B$1/[1]RELATÓRIO!$B$10,0) -> 0 | F22: =IF(D22=1,"EXCELENTE",IF(C22>$D$1,"ÓTIMO", IF(C22=$D$1,"BOM","PODE MELHORAR"))) -> ÓTIMO | G22: =IF(F22="ÓTIMO","Viagem para Natal",IF(AND(C22<=$D$1, C22 >= 100000),"Computador","")) -> Viagem para Natal

Sheet RELATÓRIO
A1: VENDAS | D1: USADOS
A2: Maior | B2: =MAX(VENDAS!C3:C22) -> 150000 | D2: Total Vendedores | E2: =COUNTIF(VENDAS!B3:B22,RELATÓRIO!D1) -> 8
A3: Menor | B3: =MIN(VENDAS!C3:C22) -> 23000 | D3: Ganhadores | E3: =COUNTIFS(VENDAS!B3:B22,RELATÓRIO!D1,VENDAS!D3:D22,1) -> 0
A4: Média | B4: =AVERAGE(VENDAS!C3:C22) -> 107108.95 | D4: Média de Vendas Total | E4: =AVERAGEIF(VENDAS!B3:B22,RELATÓRIO!D1,VENDAS!C3:C22) -> 101587.5
D5: Média de Vendas dos Não Ganhadores | E5: =AVERAGEIFS(VENDAS!C3:C22,VENDAS!B3:B22,RELATÓRIO!D1,VENDAS!D3:D22,"<>1") -> 101587.5
A6: NÚMERO DE VENDEDORES
A7: Total | B7: =COUNTA(VENDAS!A3:A22) -> 20 | D7: ZERO KM
A8: Não efetuaram vendas | B8: =COUNTBLANK(VENDAS!C3:C22) -> 1 | D8: Total Vendedores | E8: =COUNTIF(VENDAS!B3:B22,RELATÓRIO!D7) -> 7
A9: Efetuaram vendas | B9: =COUNT(VENDAS!C3:C22) -> 19 | D9: Ganhadores | E9: =COUNTIFS(VENDAS!B3:B22,RELATÓRIO!D7,VENDAS!D3:D22,1) -> 1
A10: Ganhadores do prêmio | B10: =COUNTIF(VENDAS!D3:D22,1) -> 2 | D10: Média de Vendas Total | E10: =AVERAGEIF(VENDAS!B3:B22,RELATÓRIO!D7,VENDAS!C3:C22) -> 123624.29
D11: Média de Vendas dos Não Ganhadores | E11: =AVERAGEIFS(VENDAS!C3:C22,VENDAS!B3:B22,RELATÓRIO!D7,VENDAS!D3:D22,"<>1") -> 119228.33
D13: ISENÇÕES
D14: Total Vendedores | E14: =COUNTIF(VENDAS!B3:B22,RELATÓRIO!D13) -> 5
D15: Ganhadores | E15: =COUNTIFS(VENDAS!B3:B22,RELATÓRIO!D13,VENDAS!D3:D22,1) -> 1
D16: Média de Vendas Total | E16: =AVERAGEIF(VENDAS!B3:B22,RELATÓRIO!D13,VENDAS!C3:C22) -> 89250
D17: Média de Vendas dos Não Ganhadores | E17: =AVERAGEIFS(VENDAS!C3:C22,VENDAS!B3:B22,RELATÓRIO!D13,VENDAS!D3:D22,"<>1") -> 69000

Sheet ITENS
A1: ITEM | B1: COR | C1: LÁPIS E VERMELHO | D1: LÁPIS OU VERMELHO
A2: Lápis | B2: Amarelo | C2: =AND(A2="Lápis",B2="Vermelho") -> FALSE | D2: =OR(A2="Lápis",B2="Vermelho") -> TRUE
A3: Caderno | B3: Verde | C3: =AND(A3="Lápis",B3="Vermelho") -> FALSE | D3: =OR(A3="Lápis",B3="Vermelho") -> FALSE
A4: Estojo | B4: Vermelho | C4: =AND(A4="Lápis",B4="Vermelho") -> FALSE | D4: =OR(A4="Lápis",B4="Vermelho") -> TRUE
A5: Pen Drive | B5: Vermelho | C5: =AND(A5="Lápis",B5="Vermelho") -> FALSE | D5: =OR(A5="Lápis",B5="Vermelho") -> TRUE
A6: Caixa | B6: Verde | C6: =AND(A6="Lápis",B6="Vermelho") -> FALSE | D6: =OR(A6="Lápis",B6="Vermelho") -> FALSE
A7: Grampeador | B7: Amarelo | C7: =AND(A7="Lápis",B7="Vermelho") -> FALSE | D7: =OR(A7="Lápis",B7="Vermelho") -> FALSE
A8: Lápis | B8: Vermelho | C8: =AND(A8="Lápis",B8="Vermelho") -> TRUE | D8: =OR(A8="Lápis",B8="Vermelho") -> TRUE
A9: Pen Drive | B9: Amarelo | C9: =AND(A9="Lápis",B9="Vermelho") -> FALSE | D9: =OR(A9="Lápis",B9="Vermelho") -> FALSE
A10: Caixa | B10: Vermelho | C10: =AND(A10="Lápis",B10="Vermelho") -> FALSE | D10: =OR(A10="Lápis",B10="Vermelho") -> TRUE
A11: Lápis | B11: Amarelo | C11: =AND(A11="Lápis",B11="Vermelho") -> FALSE | D11: =OR(A11="Lápis",B11="Vermelho") -> TRUE
A12: Caderno | B12: Verde | C12: =AND(A12="Lápis",B12="Vermelho") -> FALSE | D12: =OR(A12="Lápis",B12="Vermelho") -> FALSE
A13: Lápis | B13: Amarelo | C13: =AND(A13="Lápis",B13="Vermelho") -> FALSE | D13: =OR(A13="Lápis",B13="Vermelho") -> TRUE
... A15: Caixa | B15: Vermelho | C15: =AND(A15="Lápis",B15="Vermelho") -> FALSE | D15: =OR(A15="Lápis",B15="Vermelho") -> TRUE

Sheet META DE VENDAS
A1: Meta de Vendas: | B1: 20000
A3: Vendedor | B3: Vendas | C3: Conceito
A4: Marlene | B4: 5200 | C4: =_xlfn.IFS(B4<10000,"REGULAR",AND(B4>=10000,B4<$B$1),"BOM",B4>=$B$1,"EXCELENTE") -> REGULAR
A5: Joaquim | B5: 19000 | C5: =_xlfn.IFS(B5<10000,"REGULAR",AND(B5>=10000,B5<$B$1),"BOM",B5>=$B$1,"EXCELENTE") -> BOM
A6: Ferdinando | B6: 23000 | C6: =_xlfn.IFS(B6<10000,"REGULAR",AND(B6>=10000,B6<$B$1),"BOM",B6>=$B$1,"EXCELENTE") -> EXCELENTE
A7: Sophia | B7: 20000 | C7: =_xlfn.IFS(B7<10000,"REGULAR",AND(B7>=10000,B7<$B$1),"BOM",B7>=$B$1,"EXCELENTE") -> EXCELENTE
A8: Geraldo | B8: 3500 | C8: =_xlfn.IFS(B8<10000,"REGULAR",AND(B8>=10000,B8<$B$1),"BOM",B8>=$B$1,"EXCELENTE") -> REGULAR
A9: Augusto | B9: 5600 | C9: =_xlfn.IFS(B9<10000,"REGULAR",AND(B9>=10000,B9<$B$1),"BOM",B9>=$B$1,"EXCELENTE") -> REGULAR

Sheet CONTAS DO FABIO
A1: CONTAS DO FÁBIO
A3: Investimento para o consultório
A4: Nº Parcelas | B4: Taxa | C4: Valor da parcela | D4: Valor Futuro
A5: 60 | B5: 0.015 | C5: 500 | D5: =FV(B5,A5,C5) -> -48107.326
A7: Compra de uma máquina de lavar
A8: Nº Parcelas | B8: Taxa | C8: Valor da parcela | D8: Valor à Vista
A9: 24 | B9: 0.035 | C9: 78 | D9: =PV(B9,A9,C9) -> -1252.5527
A11: Compra de um automóvel
A12: Nº Parcelas | B12: Taxa | C12: Valor da parcela | D12: Valor do Carro
A13: 24 | B13: 0.005 | C13: =PMT(B13,A13,D13) -> -1551.2214 | D13: 35000
A15: Investimento
A16: Nº Parcelas | B16: Taxa | C16: Valor da parcela | D16: Valor desejado
A17: =NPER(B17,C17,D17) -> -18.247275 | B17: 0.024 | C17: 1551.22 | D17: 35000

Sheet FORMATACAO DE DATAS
A1: Data | B1: Dia do Mês | C1: Dia da Semana | D1: Mês | E1: Dia, Mês, Ano
A2: 40557 | B2: 40557 | C2: 40557 | D2: 40557 | E2: 40557
A3: 40565 | B3: 40565 | C3: 40565 | D3: 40565 | E3: 40565
A4: 40574 | B4: 40574 | C4: 40574 | D4: 40574 | E4: 40574
A5: 40584 | B5: 40584 | C5: 40584 | D5: 40584 | E5: 40584
A6: 40663 | B6: 40663 | C6: 40663 | D6: 40663 | E6: 40663
A7: 40674 | B7: 40674 | C7: 40674 | D7: 40674 | E7: 40674
A8: 40720 | B8: 40720 | C8: 40720 | D8: 40720 | E8: 40720
A9: 40724 | B9: 40724 | C9: 40724 | D9: 40724 | E9: 40724
A10: 40770 | B10: 40770 | C10: 40770 | D10: 40770 | E10: 40770
A11: 40796 | B11: 40796 | C11: 40796 | D11: 40796 | E11: 40796
A12: 40809 | B12: 40809 | C12: 40809 | D12: 40809 | E12: 40809
A13: 40828 | B13: 40828 | C13: 40828 | D13: 40828 | E13: 40828
... A15: 40901 | B15: 40901 | C15: 40901 | D15: 40901 | E15: 40901

Sheet ESTOQUE
A1: DATA DE HOJE: | F1: =TODAY() -> 43535
A2: DIA DE HOJE: | F2: =DAY(F1) -> 11
A3: NÚMERO DO MÊS DE HOJE: | F3: =MONTH(F1) -> 3
A4: ANO DE HOJE: | F4: =YEAR(F1) -> 2019
A5: NÚMERO DO DIA DA SEMANA DE HOJE: | F5: =WEEKDAY(F1) -> 2
A7: CONTROLE DO ESTOQUE DE VASSOURAS
A8: MÊS: | B8: 43221
A10: DATA | B10: DIA DA SEMANA | C10: ESTOQUE ANTERIOR | D10: QUANTIDADE ENTRADA | E10: QUANTIDADE SAÍDA | F10: ESTOQUE DO DIA
A11: =WORKDAY.INTL(B8-1,1,1,[2]FERIADOS!A:A) -> 43222 | B11: 43222 | C11: 10 | D11: 20 | E11: 15 | F11: =C11+D11-E11 -> 15
A12: =WORKDAY.INTL(A11,1,1,[2]FERIADOS!A:A) -> 43223 | B12: 43223 | C12: =F11 -> 15 | D12: 5 | E12: 20 | F12: =C12+D12-E12 -> 0
A13: =WORKDAY.INTL(A12,1,1,[2]FERIADOS!A:A) -> 43224 | B13: 43224 | C13: =F12 -> 0 | D13: 10 | E13: 8 | F13: =C13+D13-E13 -> 2
A14: =WORKDAY.INTL(A13,1,1,[2]FERIADOS!A:A) -> 43227 | B14: 43227 | C14: =F13 -> 2 | D14: 23 | E14: 20 | F14: =C14+D14-E14 -> 5
A15: =WORKDAY.INTL(A14,1,1,[2]FERIADOS!A:A) -> 43228 | B15: 43228 | C15: =F14 -> 5 | D15: 25 | E15: 22 | F15: =C15+D15-E15 -> 8
A16: =WORKDAY.INTL(A15,1,1,[2]FERIADOS!A:A) -> 43229 | B16: 43229 | C16: =F15 -> 8 | D16: 12 | E16: 10 | F16: =C16+D16-E16 -> 10
A17: =WORKDAY.INTL(A16,1,1,[2]FERIADOS!A:A) -> 43230 | B17: 43230 | C17: =F16 -> 10 | D17: 20 | E17: 12 | F17: =C17+D17-E17 -> 18
A18: =WORKDAY.INTL(A17,1,1,[2]FERIADOS!A:A) -> 43231 | B18: 43231 | C18: =F17 -> 18 | D18: 2 | E18: 15 | F18: =C18+D18-E18 -> 5
A19: =WORKDAY.INTL(A18,1,1,[2]FERIADOS!A:A) -> 43234 | B19: 43234 | C19: =F18 -> 5 | D19: 13 | E19: 17 | F19: =C19+D19-E19 -> 1
A20: =WORKDAY.INTL(A19,1,1,[2]FERIADOS!A:A) -> 43235 | B20: 43235 | C20: =F19 -> 1 | D20: 20 | E20: 15 | F20: =C20+D20-E20 -> 6
A21: =WORKDAY.INTL(A20,1,1,[2]FERIADOS!A:A) -> 43236 | B21: 43236 | C21: =F20 -> 6 | D21: 22 | E21: 25 | F21: =C21+D21-E21 -> 3
A22: =WORKDAY.INTL(A21,1,1,[2]FERIADOS!A:A) -> 43237 | B22: 43237 | C22: =F21 -> 3 | D22: 30 | E22: 24 | F22: =C22+D22-E22 -> 9
A23: =WORKDAY.INTL(A22,1,1,[2]FERIADOS!A:A) -> 43238 | B23: 43238 | C23: =F22 -> 9 | D23: 45 | E23: 40 | F23: =C23+D23-E23 -> 14
... A30: =WORKDAY.INTL(A29,1,1,[2]FERIADOS!A:A) -> 43249 | B30: 43249 | C30: =F29 -> 7 | D30: 13 | E30: 15 | F30: =C30+D30-E30 -> 5

Sheet FERIADOS
A1: 43221
A2: 43251

Sheet RELATORIO
A1: ZAP S/A - CONTROLE DE PAGAMENTOS ÀS EMPRESAS TERCEIRIZADAS
A2: PERÍODO: 01/01/2018 A 31/07/2018
A3: VALOR/HORA: | B3: 55
A5: EMPRESA | B5: ÁREA | C5: DATA INÍCIO CONTRATO | D5: DATA TÉRMINO CONTRATO | E5: CARGA HORÁRIA DIÁRIA | F5: DIAS ÚTEIS | G5: VALOR DO CONTRATO
A6: ADM MÃO DE OBRA | B6: Administrativa | C6: 43101 | D6: 43158 | E6: 6 | F6: =NETWORKDAYS.INTL(RELATORIO!C6,RELATORIO!D6,11,'FERIADOS-2'!A:A) -> 46 | G6: =F6*E6*$B$3 -> 15180
A7: CONTÁBIL TOTAL | B7: Contabilidade | C7: 43110 | D7: 43144 | E7: 6 | F7: =NETWORKDAYS.INTL(RELATORIO!C7,RELATORIO!D7,11,'FERIADOS-2'!A:A) -> 27 | G7: =F7*E7*$B$3 -> 8910
A8: LUCAS BROS | B8: Administrativa | C8: 43162 | D8: 43200 | E8: 8 | F8: =NETWORKDAYS.INTL(RELATORIO!C8,RELATORIO!D8,11,'FERIADOS-2'!A:A) -> 32 | G8: =F8*E8*$B$3 -> 14080
A9: CONTÁBIL TOTAL | B9: Contabilidade | C9: 43179 | D9: 43205 | E9: 4 | F9: =NETWORKDAYS.INTL(RELATORIO!C9,RELATORIO!D9,11,'FERIADOS-2'!A:A) -> 22 | G9: =F9*E9*$B$3 -> 4840
A10: LUCAS BROS | B10: Contabilidade | C10: 43222 | D10: 43250 | E10: 4 | F10: =NETWORKDAYS.INTL(RELATORIO!C10,RELATORIO!D10,11,'FERIADOS-2'!A:A) -> 25 | G10: =F10*E10*$B$3 -> 5500
A11: ADM MÃO DE OBRA | B11: Administrativa | C11: 43231 | D11: 43238 | E11: 6 | F11: =NETWORKDAYS.INTL(RELATORIO!C11,RELATORIO!D11,11,'FERIADOS-2'!A:A) -> 7 | G11: =F11*E11*$B$3 -> 2310
A12: ADM MÃO DE OBRA | B12: Administrativa | C12: 43252 | D12: 43271 | E12: 8 | F12: =NETWORKDAYS.INTL(RELATORIO!C12,RELATORIO!D12,11,'FERIADOS-2'!A:A) -> 17 | G12: =F12*E12*$B$3 -> 7480
A13: LUCAS BROS | B13: Administrativa | C13: 43261 | D13: 43286 | E13: 6 | F13: =NETWORKDAYS.INTL(RELATORIO!C13,RELATORIO!D13,11,'FERIADOS-2'!A:A) -> 22 | G13: =F13*E13*$B$3 -> 7260
A14: CONTÁBIL TOTAL | B14: Contabilidade | C14: 43262 | D14: 43274 | E14: 4 | F14: =NETWORKDAYS.INTL(RELATORIO!C14,RELATORIO!D14,11,'FERIADOS-2'!A:A) -> 12 | G14: =F14*E14*$B$3 -> 2640
A15: LUCAS BROS | B15: Administrativa | C15: 43291 | D15: 43304 | E15: 4 | F15: =NETWORKDAYS.INTL(RELATORIO!C15,RELATORIO!D15,11,'FERIADOS-2'!A:A) -> 12 | G15: =F15*E15*$B$3 -> 2640
A16: ADM MÃO DE OBRA | B16: Administrativa | C16: 43296 | D16: 43312 | E16: 8 | F16: =NETWORKDAYS.INTL(RELATORIO!C16,RELATORIO!D16,11,'FERIADOS-2'!A:A) -> 14 | G16: =F16*E16*$B$3 -> 6160

Sheet FERIADOS-2
A1: 43101
A2: 43125
A3: 43143
A4: 43144
A5: 43189
A6: 43211
A7: 43221
A8: 43251
A9: 43290

Sheet LANHOUSE
A1: NETHOUSE - COMPUTADOR 23 - 03/06/2018
A2: VALOR HORA: | B2: 10
A4: USUÁRIO | B4: HORA INICIAL | C4: HORA FINAL | D4: TEMPO TOTAL | E4: NÚMERO DE HORAS | F4: NÚMERO DE MINUTOS | G4: TEMPO TOTAL (MINUTOS) | H4: VALOR DO MINUTO | I4: VALOR A PAGAR
A5: Alexandre | B5: 0.375 | C5: 0.42013889 | D5: =C5-B5 -> 0.045138889 | E5: =HOUR(D5) -> 1 | F5: =MINUTE(D5) -> 5 | G5: =E5*60+F5 -> 65 | H5: =IF(HOUR(B5)<=11,($B$2*80%)/60,$B$2/60) -> 0.13333333 | I5: =G5*H5 -> 8.6666667
A6: Karina | B6: 0.42152778 | C6: 0.44930556 | D6: =C6-B6 -> 0.027777778 | E6: =HOUR(D6) -> 0 | F6: =MINUTE(D6) -> 40 | G6: =E6*60+F6 -> 40 | H6: =IF(HOUR(B6)<=11,($B$2*80%)/60,$B$2/60) -> 0.13333333 | I6: =G6*H6 -> 5.3333333
A7: Monica | B7: 0.45138889 | C7: 0.47916667 | D7: =C7-B7 -> 0.027777778 | E7: =HOUR(D7) -> 0 | F7: =MINUTE(D7) -> 40 | G7: =E7*60+F7 -> 40 | H7: =IF(HOUR(B7)<=11,($B$2*80%)/60,$B$2/60) -> 0.13333333 | I7: =G7*H7 -> 5.3333333
A8: Manolo | B8: 0.47986111 | C8: 0.50347222 | D8: =C8-B8 -> 0.023611111 | E8: =HOUR(D8) -> 0 | F8: =MINUTE(D8) -> 34 | G8: =E8*60+F8 -> 34 | H8: =IF(HOUR(B8)<=11,($B$2*80%)/60,$B$2/60) -> 0.13333333 | I8: =G8*H8 -> 4.5333333
A9: Simone | B9: 0.50486111 | C9: 0.57291667 | D9: =C9-B9 -> 0.068055556 | E9: =HOUR(D9) -> 1 | F9: =MINUTE(D9) -> 38 | G9: =E9*60+F9 -> 98 | H9: =IF(HOUR(B9)<=11,($B$2*80%)/60,$B$2/60) -> 0.16666667 | I9: =G9*H9 -> 16.333333
A10: Yvone | B10: 0.57361111 | C10: 0.6875 | D10: =C10-B10 -> 0.11388889 | E10: =HOUR(D10) -> 2 | F10: =MINUTE(D10) -> 44 | G10: =E10*60+F10 -> 164 | H10: =IF(HOUR(B10)<=11,($B$2*80%)/60,$B$2/60) -> 0.16666667 | I10: =G10*H10 -> 27.333333
A11: Rogerio | B11: 0.69791667 | C11: 0.75 | D11: =C11-B11 -> 0.052083333 | E11: =HOUR(D11) -> 1 | F11: =MINUTE(D11) -> 15 | G11: =E11*60+F11 -> 75 | H11: =IF(HOUR(B11)<=11,($B$2*80%)/60,$B$2/60) -> 0.16666667 | I11: =G11*H11 -> 12.5
